{
  "steps": {
    "1": {
      "time": 0,
      "communities": {
        "1": {
          "data": {
            "topic": "Topic 1"
          },
          "users": ["1", "2", "3", "4", "5", "6", "7", "8"]
        }
      }
    },
    "2": {
      "time": 3600,
      "communities": {
        "1": {
          "data": {
            "topic": "Topic 1"
          },
          "users": ["1", "2", "3", "4", "5", "6", "7", "8"]
        },
        "2": {
          "data": {
            "topic": "Topic 2"
          },
          "users": ["9", "10", "11", "12"]
        }
      }
    },
    "3": {
      "time": 7200,
      "communities": {
        "1": {
          "data": {
            "topic": "Topic 1"
          },
          "users": ["1", "2", "3", "4", "5", "6", "7", "8"]
        },
        "2": {
          "data": {
            "topic": "Topic 3"
          },
          "users": ["13", "14", "15", "16", "17", "18"]
        },
        "3": {
          "data": {
            "topic": "Topic 4"
          },
          "users": ["9", "10", "11", "12"]
        }
      }
    },
    "4": {
      "time": 10800,
      "communities": {
        "1": {
          "data": {
            "topic": "Topic 3"
          },
          "users": ["13", "14", "15", "16", "17", "18"]
        },
        "2": {
          "data": {
            "topic": "Topic 4"
          },
          "users": ["9", "10", "11", "12"]
        }
      }
    },
    "5": {
      "time": 14400,
      "communities": {
        "1": {
          "data": {
            "topic": "Topic 1"
          },
          "users": ["1", "2", "3", "4", "5", "6", "7", "8"]
        },
        "2": {
          "data": {
            "topic": "Topic 3"
          },
          "users": ["13", "14", "15"]
        },
        "3": {
          "data": {
            "topic": "Topic 5"
          },
          "users": ["16", "17", "18"]
        },
        "4": {
          "data": {
            "topic": "Topic 2"
          },
          "users": ["9", "10", "11", "12"]
        }
      }
    },
    "6": {
      "time": 18000,
      "communities": {
        "1": {
          "data": {
            "topic": "Topic 1"
          },
          "users": ["1", "2", "3", "4", "5", "6", "7", "8"]
        },
        "2": {
          "data": {
            "topic": "Topic 3"
          },
          "users": ["13", "14", "15"]
        },
        "3": {
          "data": {
            "topic": "Topic 5"
          },
          "users": ["9", "10", "11", "12", "16", "17", "18"]
        }
      }
    },
    "7": {
      "time": 21600,
      "communities": {
        "1": {
          "data": {
            "topic": "Topic 1"
          },
          "users": ["1", "2", "3", "4", "5", "6", "7", "8"]
        },
        "2": {
          "data": {
            "topic": "Topic 5"
          },
          "users": ["9", "10", "11", "12", "16", "17", "18"]
        }
      }
    },
    "8": {
      "time": 25200,
      "communities": {
        "1": {
          "data": {
            "topic": "Topic 1"
          },
          "users": ["1", "2", "3", "4", "5", "6", "7", "8"]
        }
      }
    }
  },
  "default_color_key": "topic"
}
